h2o_nitro_plotly/__init__.py
h2o_nitro_plotly/plugin.py
h2o_nitro_plotly/version.py
h2o_nitro_plotly-0.1.0.dist-info/LICENSE
h2o_nitro_plotly-0.1.0.dist-info/METADATA
h2o_nitro_plotly-0.1.0.dist-info/WHEEL
h2o_nitro_plotly-0.1.0.dist-info/top_level.txt
h2o_nitro_plotly-0.1.0.dist-info/RECORD
